astruc/__init__.py
astruc/astruc.py
astruc-0.1.dist-info/METADATA
astruc-0.1.dist-info/WHEEL
astruc-0.1.dist-info/top_level.txt
astruc-0.1.dist-info/RECORD
